autopydriver/api/__init__.py
autopydriver/api/base_instrument.py
autopydriver/api/oscilloscope.py
autopydriver/api/SCPIMixin.py
autopydriver/comm/__init__.py
autopydriver/comm/adapter.py
autopydriver/comm/visa_adapter.py
autopydriver/conf/rtm30xx.yaml
autopydriver/dist/autopydriver-0.1.0.tar.gz
autopydriver/impl/oscilloscope/__init__.py
autopydriver/impl/oscilloscope/rtm3002.py
autopydriver/utils/__init__.py
autopydriver/utils/exceptions.py
autopydriver/utils/logger.py
autopydriver/utils/validators.py
autopydriver-0.1.0.dist-info/METADATA
autopydriver-0.1.0.dist-info/WHEEL
autopydriver-0.1.0.dist-info/RECORD
