Metadata-Version: 2.3
Name: autopydriver
Version: 0.1.0
Summary: 
Author: Kvelmi
Author-email: ilya23016@gmail.com
Requires-Python: >=3.12
Classifier: Programming Language :: Python :: 3
Classifier: Programming Language :: Python :: 3.12
Classifier: Programming Language :: Python :: 3.13
Requires-Dist: numpy (>=2.2.6,<3.0.0)
Requires-Dist: psutil (>=7.0.0,<8.0.0)
Requires-Dist: pyserial (>=3.5,<4.0)
Requires-Dist: pyusb (>=1.3.1,<2.0.0)
Requires-Dist: pyvisa (>=1.15.0,<2.0.0)
Requires-Dist: pyvisa-sim (>=0.7.0,<0.8.0)
